<?xml version="1.0"?>

<resource xmlns="http://www.wyona.org/yanel/1.0"
  name="calendar"
  namespace="http://www.wyona.org/yanel/resource/1.0"
  class="org.wyona.yanel.impl.resources.calendar.CalendarResource"
  >
<description>
Calendar resource based on ICS format, whereas the calendar can also be generated by aggregating the various XML events by calling the XML view, e.g. http://127.0.0.1:8080/yanel/test/use-cases/calendar.ics?yanel.resource.viewid=xml
</description>

<rtd>
  <property name="classes"/>
  <property name="categories"/>
  <property name="user-ids"/>

  <!-- Path where events as individual XML documents are located -->
  <property name="events-path"/>
<!--
  <property name="yarep-repository-id"/>
-->

  <property name="mime-type" default-value="text/calendar"/>
</rtd>
</resource>
